tinydb_viewer/__init__.py
tinydb_viewer/api.py
tinydb_viewer/config.py
tinydb_viewer/main.py
tinydb_viewer/renderer.py
tinydb_viewer/table.py
tinydb_viewer/templates/handsontable.full.min.css
tinydb_viewer/templates/handsontable.full.min.js
tinydb_viewer/templates/viewer.html
tinydb_viewer/templates/viewer.js
tinydb_viewer/util.py
tinydb_viewer/views.py
tinydb_viewer-0.2.7.dist-info/LICENSE
tinydb_viewer-0.2.7.dist-info/WHEEL
tinydb_viewer-0.2.7.dist-info/METADATA
tinydb_viewer-0.2.7.dist-info/RECORD
